tensorflow_ml/__init__.py
tensorflow_ml/classification/__init__.py
tensorflow_ml/classification/decision_tree.py
tensorflow_ml/classification/logistic_regression.py
tensorflow_ml/classification/naive_bayes/__init__.py
tensorflow_ml/classification/naive_bayes/bernoulli.py
tensorflow_ml/classification/naive_bayes/gaussian.py
tensorflow_ml/regression/__init__.py
tensorflow_ml/regression/lasso.py
tensorflow_ml/regression/linear.py
tensorflow_ml/regression/polynomial.py
tensorflow_ml/regression/ridge.py
tensorflow_ml-1.1.3.2.dist-info/LICENSE
tensorflow_ml-1.1.3.2.dist-info/METADATA
tensorflow_ml-1.1.3.2.dist-info/WHEEL
tensorflow_ml-1.1.3.2.dist-info/top_level.txt
tensorflow_ml-1.1.3.2.dist-info/RECORD
