Metadata-Version: 2.1
Name: tensorflow-ml
Version: 1.1.3.2
Summary: Tensorflow ML
Author: Siddhant Pathak
Author-email: siddhantpathak2@gmail.com
Keywords: python,tensorflow,ml,keras
Classifier: Programming Language :: Python :: 3
Classifier: Operating System :: MacOS :: MacOS X
Classifier: Operating System :: POSIX :: Linux
License-File: LICENSE
Requires-Dist: absl-py ==1.4.0
Requires-Dist: aiofiles ==23.1.0
Requires-Dist: aiosqlite ==0.19.0
Requires-Dist: anyio ==3.7.1
Requires-Dist: appdirs ==1.4.4
Requires-Dist: appnope ==0.1.3
Requires-Dist: argon2-cffi ==21.3.0
Requires-Dist: argon2-cffi-bindings ==21.2.0
Requires-Dist: arrow ==1.2.3
Requires-Dist: asttokens ==2.2.1
Requires-Dist: astunparse ==1.6.3
Requires-Dist: async-lru ==2.0.4
Requires-Dist: attrs ==23.1.0
Requires-Dist: Babel ==2.12.1
Requires-Dist: backcall ==0.2.0
Requires-Dist: beautifulsoup4 ==4.12.2
Requires-Dist: bleach ==6.0.0
Requires-Dist: blosc2 ==2.0.0
Requires-Dist: Bottleneck ==1.3.7
Requires-Dist: brotlipy ==0.7.0
Requires-Dist: cachetools ==5.3.1
Requires-Dist: certifi ==2023.5.7
Requires-Dist: cffi ==1.15.1
Requires-Dist: chardet ==3.0.4
Requires-Dist: charset-normalizer ==3.2.0
Requires-Dist: cloudpickle ==2.2.1
Requires-Dist: colorlover ==0.3.0
Requires-Dist: comm ==0.1.4
Requires-Dist: contourpy ==1.1.0
Requires-Dist: cryptography ==41.0.3
Requires-Dist: cufflinks ==0.17.3
Requires-Dist: cycler ==0.11.0
Requires-Dist: Cython ==3.0.0b3
Requires-Dist: DateTime ==5.1
Requires-Dist: debugpy ==1.6.7
Requires-Dist: decorator <5.0
Requires-Dist: defusedxml ==0.7.1
Requires-Dist: deprecation ==2.1.0
Requires-Dist: dm-tree ==0.1.8
Requires-Dist: eikon ==1.1.16
Requires-Dist: entrypoints ==0.4
Requires-Dist: et-xmlfile ==1.1.0
Requires-Dist: executing ==1.2.0
Requires-Dist: fastjsonschema ==2.18.0
Requires-Dist: flatbuffers ==23.5.26
Requires-Dist: fonttools ==4.25.0
Requires-Dist: fqdn ==1.5.1
Requires-Dist: frozendict ==2.3.8
Requires-Dist: gast ==0.4.0
Requires-Dist: google-auth
Requires-Dist: google-auth-oauthlib ==1.0.0
Requires-Dist: google-pasta ==0.2.0
Requires-Dist: grpcio ==1.56.0
Requires-Dist: h11 ==0.14.0
Requires-Dist: h2 ==3.2.0
Requires-Dist: h5py ==3.9.0
Requires-Dist: hpack ==3.0.0
Requires-Dist: html5lib ==1.1
Requires-Dist: httpcore ==0.17.3
Requires-Dist: httpx ==0.24.1
Requires-Dist: hyperframe ==5.2.0
Requires-Dist: idna ==2.10
Requires-Dist: inflection ==0.5.1
Requires-Dist: ipython
Requires-Dist: ipython-genutils ==0.2.0
Requires-Dist: ipywidgets ==8.1.0
Requires-Dist: isoduration ==20.11.0
Requires-Dist: jax ==0.4.13
Requires-Dist: jedi ==0.19.0
Requires-Dist: Jinja2 ==3.1.2
Requires-Dist: joblib ==1.3.1
Requires-Dist: json5 ==0.9.14
Requires-Dist: jsonpointer ==2.4
Requires-Dist: jsonschema ==4.18.6
Requires-Dist: jsonschema-specifications ==2023.7.1
Requires-Dist: jupyter ==1.0.0
Requires-Dist: jupyterlab ==4.0.4
Requires-Dist: keras ==2.13.1
Requires-Dist: kiwisolver ==1.4.4
Requires-Dist: libclang ==16.0.0
Requires-Dist: lxml ==4.9.3
Requires-Dist: Markdown ==3.4.3
Requires-Dist: MarkupSafe ==2.1.3
Requires-Dist: matplotlib ==3.7.2
Requires-Dist: matplotlib-inline ==0.1.6
Requires-Dist: mistune ==3.0.1
Requires-Dist: ml-dtypes ==0.2.0
Requires-Dist: more-itertools ==10.1.0
Requires-Dist: msgpack ==1.0.5
Requires-Dist: multitasking ==0.0.11
Requires-Dist: munkres ==1.1.4
Requires-Dist: nbclassic ==1.0.0
Requires-Dist: nbclient ==0.8.0
Requires-Dist: nbconvert ==7.7.3
Requires-Dist: nbformat ==5.9.2
Requires-Dist: nest-asyncio ==1.5.7
Requires-Dist: notebook
Requires-Dist: notebook-shim ==0.2.3
Requires-Dist: numexpr ==2.8.4
Requires-Dist: numpy ==1.23.5
Requires-Dist: oauthlib ==3.2.2
Requires-Dist: openpyxl ==3.0.10
Requires-Dist: opt-einsum ==3.3.0
Requires-Dist: overrides ==7.3.1
Requires-Dist: packaging ==23.1
Requires-Dist: pandas ==1.5.3
Requires-Dist: pandas-datareader ==0.10.0
Requires-Dist: pandocfilters ==1.5.0
Requires-Dist: parso ==0.8.3
Requires-Dist: patsy ==0.5.3
Requires-Dist: pexpect ==4.8.0
Requires-Dist: pickleshare ==0.7.5
Requires-Dist: Pillow ==9.4.0
Requires-Dist: platformdirs ==3.10.0
Requires-Dist: plotly ==5.15.0
Requires-Dist: ply ==3.11
Requires-Dist: pooch <1.7
Requires-Dist: prometheus-client ==0.17.1
Requires-Dist: prompt-toolkit ==3.0.39
Requires-Dist: protobuf ==4.23.3
Requires-Dist: psutil ==5.9.5
Requires-Dist: ptyprocess ==0.7.0
Requires-Dist: pure-eval ==0.2.2
Requires-Dist: py-cpuinfo ==9.0.0
Requires-Dist: pyasn1 ==0.5.0
Requires-Dist: pyasn1-modules ==0.3.0
Requires-Dist: pycparser ==2.21
Requires-Dist: Pygments ==2.15.1
Requires-Dist: pyOpenSSL ==23.2.0
Requires-Dist: pyparsing ==3.0.9
Requires-Dist: PyQt5-sip ==12.11.0
Requires-Dist: pyrsistent ==0.19.3
Requires-Dist: PySocks ==1.7.1
Requires-Dist: python-dateutil ==2.8.2
Requires-Dist: python-json-logger ==2.0.7
Requires-Dist: pytz ==2023.3
Requires-Dist: PyYAML ==6.0.1
Requires-Dist: pyzmq ==25.1.0
Requires-Dist: qtconsole ==5.4.3
Requires-Dist: QtPy ==2.3.1
Requires-Dist: referencing ==0.30.2
Requires-Dist: requests-oauthlib ==1.3.1
Requires-Dist: rfc3339-validator ==0.1.4
Requires-Dist: rfc3986 ==1.5.0
Requires-Dist: rfc3986-validator ==0.1.1
Requires-Dist: rpds-py ==0.9.2
Requires-Dist: rsa ==4.9
Requires-Dist: scipy ==1.11.1
Requires-Dist: Send2Trash ==1.8.2
Requires-Dist: six ==1.16.0
Requires-Dist: sniffio ==1.3.0
Requires-Dist: soupsieve ==2.4.1
Requires-Dist: stack-data ==0.6.2
Requires-Dist: statsmodels ==0.14.0
Requires-Dist: tenacity ==8.2.2
Requires-Dist: tensorboard ==2.13.0
Requires-Dist: tensorboard-data-server ==0.7.1
Requires-Dist: tensorflow-decision-forests ==1.5.0
Requires-Dist: tensorflow-estimator ==2.13.0
Requires-Dist: tensorflow ==2.13.0
Requires-Dist: tensorflow-probability ==0.21.0
Requires-Dist: termcolor ==2.3.0
Requires-Dist: terminado ==0.17.1
Requires-Dist: tinycss2 ==1.2.1
Requires-Dist: tornado ==6.3.1
Requires-Dist: traitlets ==5.9.0
Requires-Dist: typing-extensions ==4.5.0
Requires-Dist: uri-template ==1.3.0
Requires-Dist: urllib3 ==1.26.16
Requires-Dist: wcwidth ==0.2.6
Requires-Dist: webcolors ==1.13
Requires-Dist: webencodings ==0.5.1
Requires-Dist: websocket-client ==1.6.1
Requires-Dist: Werkzeug ==2.3.6
Requires-Dist: widgetsnbextension ==4.0.8
Requires-Dist: wrapt ==1.14.1
Requires-Dist: wurlitzer ==3.0.3
Requires-Dist: zope.interface ==6.0
